setup.py
pyelliptic/__init__.py
pyelliptic/cipher.py
pyelliptic/hash.py
pyelliptic/openssl.py
pyelliptic.egg-info/PKG-INFO
pyelliptic.egg-info/SOURCES.txt
pyelliptic.egg-info/dependency_links.txt
pyelliptic.egg-info/top_level.txt