Metadata-Version: 1.1
Name: pyelliptic
Version: 1.5.8
Summary: Python OpenSSL wrapper for modern cryptography with ECC, AES, HMAC, Blowfish, ...
Home-page: https://github.com/yann2192/pyelliptic
Author: Yann GUIBET
Author-email: yannguibet@gmail.com
License: BSD
Platform: UNKNOWN
Classifier: Operating System :: Unix
Classifier: Operating System :: Microsoft :: Windows
Classifier: Environment :: MacOS X
Classifier: Programming Language :: Python
Classifier: Programming Language :: Python :: 2.7
Classifier: Programming Language :: Python :: 3
Classifier: Topic :: Security :: Cryptography
